tendo/__init__.py
tendo/ansiterm.py
tendo/colorer.py
tendo/execfile2.py
tendo/singleton.py
tendo/tee.py
tendo/unicode.py
tendo/tests/__init__.py
tendo/tests/full_sample_utf8_bom.txt
tendo/tests/sample_ucs2_be.txt
tendo/tests/sample_ucs2_le.txt
tendo/tests/sample_utf8.txt
tendo/tests/sample_utf8_bom.txt
tendo/tests/utf8-after-append.txt
tendo/tests/utf8-invalid.txt
tendo/tests/utf8.txt
tendo-0.2.12.dist-info/METADATA
tendo-0.2.12.dist-info/RECORD
tendo-0.2.12.dist-info/WHEEL
tendo-0.2.12.dist-info/entry_points.txt
tendo-0.2.12.dist-info/pbr.json
tendo-0.2.12.dist-info/top_level.txt
