Metadata-Version: 1.2
Name: tendo
Version: 0.2.12
Summary: A Python library that extends some core functionality
Home-page: https://github.com/pycontribs/tendo
Author: Sorin Sbarnea
Author-email: sorin.sbarnea@gmail.com
Maintainer: Sorin Sbarnea
Maintainer-email: sorin.sbarnea@gmail.com
License: BSD
Keywords: tendo
Platform: UNKNOWN
Classifier: Development Status :: 5 - Production/Stable
Classifier: Environment :: Other Environment
Classifier: Intended Audience :: Developers
Classifier: Intended Audience :: Information Technology
Classifier: License :: OSI Approved :: BSD License
Classifier: Operating System :: OS Independent
Classifier: Programming Language :: Python
Classifier: Programming Language :: Python :: 2.7
Classifier: Programming Language :: Python :: 3
Classifier: Programming Language :: Python :: 3.5
Classifier: Programming Language :: Python :: 3.6
Classifier: Topic :: Software Development :: Libraries :: Python Modules
Classifier: Topic :: Internet :: WWW/HTTP
